tdwrapper/tdwrapper.py
tdwrapper/__init__.py
tdwrapper-0.0.1.dist-info/top_level.txt
tdwrapper-0.0.1.dist-info/METADATA
tdwrapper-0.0.1.dist-info/pbr.json
tdwrapper-0.0.1.dist-info/DESCRIPTION.rst
tdwrapper-0.0.1.dist-info/metadata.json
tdwrapper-0.0.1.dist-info/WHEEL
tdwrapper-0.0.1.dist-info/RECORD
