Metadata-Version: 2.0
Name: tdwrapper
Version: 0.0.1
Summary: Teradata utility wrapper for Python
Home-page: https://github.com/changhyeoklee/tdwrapper
Author: Changhyeok Lee
Author-email: Changhyeoklee@gmail.com
License: MIT
Platform: UNKNOWN
Requires-Dist: subprocess32
Requires-Dist: pandas
